Metadata-Version: 1.1
Name: AlgebraOnMatrix
Version: 0.0.1
Summary: Algebric operations on matrices
Home-page: https://github.com/preranagawale/portfolio_test1
Author: Prerana
Author-email: prerana.gawale@gmail.com
License: UNKNOWN
Platform: UNKNOWN
Classifier: Programming Language :: Python :: 3
Classifier: License :: OSI Approved :: MIT License
Classifier: Operating System :: OS Independent
